pydrafig/__init__.py
pydrafig/base_config.py
pydrafig/cli.py
pydrafig-0.1.3.dist-info/METADATA
pydrafig-0.1.3.dist-info/WHEEL
pydrafig-0.1.3.dist-info/top_level.txt
pydrafig-0.1.3.dist-info/RECORD
