Metadata-Version: 2.4
Name: pydrafig
Version: 0.1.3
Summary: Dataclass-based configuration system with strict validation and auto-finalization.
Author-email: Your Name <your.email@example.com>
License: MIT
Project-URL: Homepage, https://github.com/owendugan/pydrafig
Project-URL: Bug Tracker, https://github.com/owendugan/pydrafig/issues
Classifier: Programming Language :: Python :: 3
Classifier: License :: OSI Approved :: MIT License
Classifier: Operating System :: OS Independent
Requires-Python: >=3.10
Requires-Dist: PyYAML>=6.0
Requires-Dist: dill>=0.3.0
Provides-Extra: test
Requires-Dist: pytest>=7.0; extra == "test"
Requires-Dist: numpy; extra == "test"
Requires-Dist: torch; extra == "test"
